{
  "sections": {
    "breadcrumbs": {
      "type": "breadcrumbs",
      "settings": {
      }
    },
    "main": {
      "type": "collection-template",
      "settings": {
        "collection_tags_enable": true,
        "collection_tags_count": true,
        "collection_multiple_tags_filtering_enable": true,
        "collection_sort_enable": true,
        "tag_selector": "button",
        "collection_layout": "list",
        "rows": "4",
        "desktop_grid": "4",
        "mobile_grid": "2"
      }
    },
    "collection-image": {
      "type": "collection-image",
      "settings": {
      }
    }
  },
  "order": [
    "breadcrumbs",
    "main",
    "collection-image"
  ]
}